biocode_fims/__init__.py
biocode_fims/biocode_fims.py
biocode_fims/cli.py
biocode_fims-0.2.4.dist-info/DESCRIPTION.rst
biocode_fims-0.2.4.dist-info/METADATA
biocode_fims-0.2.4.dist-info/RECORD
biocode_fims-0.2.4.dist-info/WHEEL
biocode_fims-0.2.4.dist-info/entry_points.txt
biocode_fims-0.2.4.dist-info/metadata.json
biocode_fims-0.2.4.dist-info/top_level.txt
