Metadata-Version: 2.0
Name: biocode-fims
Version: 0.2.4
Summary: A Python client for accessing data from the Biocode FIMS database.
Home-page: https://github.com/MikeTrizna/biocode_fims
Author: Mike Trizna
Author-email: mike.trizna@gmail.com
License: MIT license
Keywords: biocode_fims
Platform: UNKNOWN
Classifier: Development Status :: 4 - Beta
Classifier: Intended Audience :: Developers
Classifier: License :: OSI Approved :: MIT License
Classifier: Natural Language :: English
Classifier: Programming Language :: Python :: 2
Classifier: Programming Language :: Python :: 2.7
Classifier: Programming Language :: Python :: 3
Classifier: Programming Language :: Python :: 3.5
Classifier: Programming Language :: Python :: 3.6
Requires-Dist: Click (>=6.0)
Requires-Dist: pandas
Requires-Dist: requests
